errorcalcs/__init__.py
errorcalcs/add.py
errorcalcs/calc.py
errorcalcs/errorcalcs.py
errorcalcs/testcalcs.py
errorcalcs-0.3.4.dist-info/LICENSE
errorcalcs-0.3.4.dist-info/METADATA
errorcalcs-0.3.4.dist-info/WHEEL
errorcalcs-0.3.4.dist-info/top_level.txt
errorcalcs-0.3.4.dist-info/RECORD
