Metadata-Version: 2.1
Name: errorcalcs
Version: 0.3.4
Summary: GUI for error calulations
Home-page: https://github.com/leonfrcom/ErroRCalcS
Author: lefrcom
Author-email: lefrcom@gmx.de
License: UNKNOWN
Platform: UNKNOWN
Classifier: Programming Language :: Python :: 3
Classifier: License :: OSI Approved :: MIT License
Classifier: Operating System :: OS Independent
Requires-Dist: uncertainties
Requires-Dist: PyQt5
